hack4u/__init__.py
hack4u/courses.py
hack4u/utils.py
pruebacurso-0.1.0.dist-info/METADATA
pruebacurso-0.1.0.dist-info/WHEEL
pruebacurso-0.1.0.dist-info/top_level.txt
pruebacurso-0.1.0.dist-info/RECORD
