Metadata-Version: 2.4
Name: PruebaCurso
Version: 0.1.0
Summary: Biblioteca para consultar cursos de hack4u a modo de aprendizaje
Home-page: https://hack4u.io
Author: Off_Klix
Dynamic: author
Dynamic: description
Dynamic: description-content-type
Dynamic: home-page
Dynamic: summary
